{"DllCharacteristics": [], "FILE_HEADER": {"NumberOfSections": {"FileOffset": 198, "Value": 3, "Offset": 2}, "TimeDateStamp": {"FileOffset": 200, "Value": "0x46A62AD9 [Tue Jul 24 16:37:45 2007 UTC]", "Offset": 4}, "PointerToSymbolTable": {"FileOffset": 204, "Value": 0, "Offset": 8}, "NumberOfSymbols": {"FileOffset": 208, "Value": 0, "Offset": 12}, "Machine": {"FileOffset": 196, "Value": 332, "Offset": 0}, "Characteristics": {"FileOffset": 214, "Value": 271, "Offset": 18}, "SizeOfOptionalHeader": {"FileOffset": 212, "Value": 224, "Offset": 16}, "Structure": "IMAGE_FILE_HEADER"}, "Parsing Warnings": ["Suspicious flags set for section 0. Both IMAGE_SCN_MEM_WRITE and IMAGE_SCN_MEM_EXECUTE are set. This might indicate a packed executable.", "Suspicious flags set for section 1. Both IMAGE_SCN_MEM_WRITE and IMAGE_SCN_MEM_EXECUTE are set. This might indicate a packed executable.", "Imported symbols contain entries typical of packed executables."], "Directories": [{"VirtualAddress": {"FileOffset": 312, "Value": 0, "Offset": 0}, "Structure": "IMAGE_DIRECTORY_ENTRY_EXPORT", "Size": {"FileOffset": 316, "Value": 0, "Offset": 4}}, {"VirtualAddress": {"FileOffset": 320, "Value": 217868, "Offset": 0}, "Structure": "IMAGE_DIRECTORY_ENTRY_IMPORT", "Size": {"FileOffset": 324, "Value": 332, "Offset": 4}}, {"VirtualAddress": {"FileOffset": 328, "Value": 217088, "Offset": 0}, "Structure": "IMAGE_DIRECTORY_ENTRY_RESOURCE", "Size": {"FileOffset": 332, "Value": 780, "Offset": 4}}, {"VirtualAddress": {"FileOffset": 336, "Value": 0, "Offset": 0}, "Structure": "IMAGE_DIRECTORY_ENTRY_EXCEPTION", "Size": {"FileOffset": 340, "Value": 0, "Offset": 4}}, {"VirtualAddress": {"FileOffset": 344, "Value": 0, "Offset": 0}, "Structure": "IMAGE_DIRECTORY_ENTRY_SECURITY", "Size": {"FileOffset": 348, "Value": 0, "Offset": 4}}, {"VirtualAddress": {"FileOffset": 352, "Value": 0, "Offset": 0}, "Structure": "IMAGE_DIRECTORY_ENTRY_BASERELOC", "Size": {"FileOffset": 356, "Value": 0, "Offset": 4}}, {"VirtualAddress": {"FileOffset": 360, "Value": 0, "Offset": 0}, "Structure": "IMAGE_DIRECTORY_ENTRY_DEBUG", "Size": {"FileOffset": 364, "Value": 0, "Offset": 4}}, {"VirtualAddress": {"FileOffset": 368, "Value": 0, "Offset": 0}, "Structure": "IMAGE_DIRECTORY_ENTRY_COPYRIGHT", "Size": {"FileOffset": 372, "Value": 0, "Offset": 4}}, {"VirtualAddress": {"FileOffset": 376, "Value": 0, "Offset": 0}, "Structure": "IMAGE_DIRECTORY_ENTRY_GLOBALPTR", "Size": {"FileOffset": 380, "Value": 0, "Offset": 4}}, {"VirtualAddress": {"FileOffset": 384, "Value": 0, "Offset": 0}, "Structure": "IMAGE_DIRECTORY_ENTRY_TLS", "Size": {"FileOffset": 388, "Value": 0, "Offset": 4}}, {"VirtualAddress": {"FileOffset": 392, "Value": 0, "Offset": 0}, "Structure": "IMAGE_DIRECTORY_ENTRY_LOAD_CONFIG", "Size": {"FileOffset": 396, "Value": 0, "Offset": 4}}, {"VirtualAddress": {"FileOffset": 400, "Value": 0, "Offset": 0}, "Structure": "IMAGE_DIRECTORY_ENTRY_BOUND_IMPORT", "Size": {"FileOffset": 404, "Value": 0, "Offset": 4}}, {"VirtualAddress": {"FileOffset": 408, "Value": 217968, "Offset": 0}, "Structure": "IMAGE_DIRECTORY_ENTRY_IAT", "Size": {"FileOffset": 412, "Value": 48, "Offset": 4}}, {"VirtualAddress": {"FileOffset": 416, "Value": 0, "Offset": 0}, "Structure": "IMAGE_DIRECTORY_ENTRY_DELAY_IMPORT", "Size": {"FileOffset": 420, "Value": 0, "Offset": 4}}, {"VirtualAddress": {"FileOffset": 424, "Value": 0, "Offset": 0}, "Structure": "IMAGE_DIRECTORY_ENTRY_COM_DESCRIPTOR", "Size": {"FileOffset": 428, "Value": 0, "Offset": 4}}, {"VirtualAddress": {"FileOffset": 432, "Value": 0, "Offset": 0}, "Structure": "IMAGE_DIRECTORY_ENTRY_RESERVED", "Size": {"FileOffset": 436, "Value": 0, "Offset": 4}}], "OPTIONAL_HEADER": {"DllCharacteristics": {"FileOffset": 286, "Value": 0, "Offset": 70}, "BaseOfCode": {"FileOffset": 236, "Value": 65536, "Offset": 20}, "MajorLinkerVersion": {"FileOffset": 218, "Value": 5, "Offset": 2}, "MinorOperatingSystemVersion": {"FileOffset": 258, "Value": 0, "Offset": 42}, "MinorLinkerVersion": {"FileOffset": 219, "Value": 12, "Offset": 3}, "MajorSubsystemVersion": {"FileOffset": 264, "Value": 4, "Offset": 48}, "MajorOperatingSystemVersion": {"FileOffset": 256, "Value": 4, "Offset": 40}, "SizeOfStackCommit": {"FileOffset": 292, "Value": 4096, "Offset": 76}, "SizeOfUninitializedData": {"FileOffset": 228, "Value": 61440, "Offset": 12}, "NumberOfRvaAndSizes": {"FileOffset": 308, "Value": 16, "Offset": 92}, "SizeOfHeapReserve": {"FileOffset": 296, "Value": 1048576, "Offset": 80}, "LoaderFlags": {"FileOffset": 304, "Value": 0, "Offset": 88}, "SizeOfHeapCommit": {"FileOffset": 300, "Value": 4096, "Offset": 84}, "SizeOfStackReserve": {"FileOffset": 288, "Value": 1048576, "Offset": 72}, "Structure": "IMAGE_OPTIONAL_HEADER", "SizeOfHeaders": {"FileOffset": 276, "Value": 4096, "Offset": 60}, "Subsystem": {"FileOffset": 284, "Value": 2, "Offset": 68}, "Magic": {"FileOffset": 216, "Value": 267, "Offset": 0}, "MinorImageVersion": {"FileOffset": 262, "Value": 0, "Offset": 46}, "MajorImageVersion": {"FileOffset": 260, "Value": 4, "Offset": 44}, "FileAlignment": {"FileOffset": 252, "Value": 512, "Offset": 36}, "BaseOfData": {"FileOffset": 240, "Value": 217088, "Offset": 24}, "AddressOfEntryPoint": {"FileOffset": 232, "Value": 214592, "Offset": 16}, "SectionAlignment": {"FileOffset": 248, "Value": 4096, "Offset": 32}, "SizeOfCode": {"FileOffset": 220, "Value": 151552, "Offset": 4}, "ImageBase": {"FileOffset": 244, "Value": 4194304, "Offset": 28}, "SizeOfInitializedData": {"FileOffset": 224, "Value": 4096, "Offset": 8}, "SizeOfImage": {"FileOffset": 272, "Value": 221184, "Offset": 56}, "MinorSubsystemVersion": {"FileOffset": 266, "Value": 0, "Offset": 50}, "CheckSum": {"FileOffset": 280, "Value": 0, "Offset": 64}, "Reserved1": {"FileOffset": 268, "Value": 0, "Offset": 52}}, "DOS_HEADER": {"e_cblp": {"FileOffset": 2, "Value": 144, "Offset": 2}, "e_crlc": {"FileOffset": 6, "Value": 0, "Offset": 6}, "e_ovno": {"FileOffset": 26, "Value": 0, "Offset": 26}, "e_minalloc": {"FileOffset": 10, "Value": 0, "Offset": 10}, "e_csum": {"FileOffset": 18, "Value": 0, "Offset": 18}, "e_cparhdr": {"FileOffset": 8, "Value": 4, "Offset": 8}, "e_cp": {"FileOffset": 4, "Value": 3, "Offset": 4}, "e_cs": {"FileOffset": 22, "Value": 0, "Offset": 22}, "e_maxalloc": {"FileOffset": 12, "Value": 65535, "Offset": 12}, "e_lfarlc": {"FileOffset": 24, "Value": 64, "Offset": 24}, "e_oemid": {"FileOffset": 36, "Value": 0, "Offset": 36}, "e_lfanew": {"FileOffset": 60, "Value": 192, "Offset": 60}, "e_ss": {"FileOffset": 14, "Value": 0, "Offset": 14}, "e_magic": {"FileOffset": 0, "Value": 23117, "Offset": 0}, "e_oeminfo": {"FileOffset": 38, "Value": 0, "Offset": 38}, "e_res2": {"FileOffset": 40, "Value": "", "Offset": 40}, "e_res": {"FileOffset": 28, "Value": "", "Offset": 28}, "e_sp": {"FileOffset": 16, "Value": 184, "Offset": 16}, "Structure": "IMAGE_DOS_HEADER", "e_ip": {"FileOffset": 20, "Value": 0, "Offset": 20}}, "NT_HEADERS": {"Structure": "IMAGE_NT_HEADERS", "Signature": {"FileOffset": 192, "Value": 17744, "Offset": 0}}, "Flags": ["IMAGE_FILE_LOCAL_SYMS_STRIPPED", "IMAGE_FILE_32BIT_MACHINE", "IMAGE_FILE_EXECUTABLE_IMAGE", "IMAGE_FILE_LINE_NUMS_STRIPPED", "IMAGE_FILE_RELOCS_STRIPPED"], "Version Information": [{"ValueLength": {"FileOffset": 150622, "Value": 52, "Offset": 2}, "Length": {"FileOffset": 150620, "Value": 688, "Offset": 0}, "Type": {"FileOffset": 150624, "Value": 0, "Offset": 4}, "Structure": "VS_VERSIONINFO"}, {"FileFlagsMask": {"FileOffset": 150684, "Value": 63, "Offset": 24}, "FileType": {"FileOffset": 150696, "Value": 1, "Offset": 36}, "FileVersionMS": {"FileOffset": 150668, "Value": 196610, "Offset": 8}, "FileVersionLS": {"FileOffset": 150672, "Value": 0, "Offset": 12}, "Signature": {"FileOffset": 150660, "Value": 4277077181, "Offset": 0}, "FileSubtype": {"FileOffset": 150700, "Value": 0, "Offset": 40}, "FileFlags": {"FileOffset": 150688, "Value": 0, "Offset": 28}, "FileDateLS": {"FileOffset": 150708, "Value": 0, "Offset": 48}, "ProductVersionLS": {"FileOffset": 150680, "Value": 0, "Offset": 20}, "FileOS": {"FileOffset": 150692, "Value": 262148, "Offset": 32}, "ProductVersionMS": {"FileOffset": 150676, "Value": 196610, "Offset": 16}, "FileDateMS": {"FileOffset": 150704, "Value": 0, "Offset": 44}, "Structure": "VS_FIXEDFILEINFO", "StrucVersion": {"FileOffset": 150664, "Value": 65536, "Offset": 4}}], "Imported symbols": [[{"TimeDateStamp": {"FileOffset": 151312, "Value": "0x0        [Thu Jan  1 00:00:00 1970 UTC]", "Offset": 4}, "Name": {"FileOffset": 151320, "Value": 218020, "Offset": 12}, "ForwarderChain": {"FileOffset": 151316, "Value": 0, "Offset": 8}, "OriginalFirstThunk": {"FileOffset": 151308, "Value": 0, "Offset": 0}, "FirstThunk": {"FileOffset": 151324, "Value": 217968, "Offset": 16}, "Characteristics": {"FileOffset": 151308, "Value": 0, "Offset": 0}, "Structure": "IMAGE_IMPORT_DESCRIPTOR"}, {"Hint": 0, "Name": "LoadLibraryA", "DLL": "KERNEL32.DLL"}, {"Hint": 0, "Name": "GetProcAddress", "DLL": "KERNEL32.DLL"}, {"Hint": 0, "Name": "VirtualProtect", "DLL": "KERNEL32.DLL"}, {"Hint": 0, "Name": "VirtualAlloc", "DLL": "KERNEL32.DLL"}, {"Hint": 0, "Name": "VirtualFree", "DLL": "KERNEL32.DLL"}, {"Hint": 0, "Name": "ExitProcess", "DLL": "KERNEL32.DLL"}], [{"TimeDateStamp": {"FileOffset": 151332, "Value": "0x0        [Thu Jan  1 00:00:00 1970 UTC]", "Offset": 4}, "Name": {"FileOffset": 151340, "Value": 218033, "Offset": 12}, "ForwarderChain": {"FileOffset": 151336, "Value": 0, "Offset": 8}, "OriginalFirstThunk": {"FileOffset": 151328, "Value": 0, "Offset": 0}, "FirstThunk": {"FileOffset": 151344, "Value": 217996, "Offset": 16}, "Characteristics": {"FileOffset": 151328, "Value": 0, "Offset": 0}, "Structure": "IMAGE_IMPORT_DESCRIPTOR"}, {"Hint": 0, "Name": "CreateStatusWindowW", "DLL": "comctl32"}], [{"TimeDateStamp": {"FileOffset": 151352, "Value": "0x0        [Thu Jan  1 00:00:00 1970 UTC]", "Offset": 4}, "Name": {"FileOffset": 151360, "Value": 218042, "Offset": 12}, "ForwarderChain": {"FileOffset": 151356, "Value": 0, "Offset": 8}, "OriginalFirstThunk": {"FileOffset": 151348, "Value": 0, "Offset": 0}, "FirstThunk": {"FileOffset": 151364, "Value": 218004, "Offset": 16}, "Characteristics": {"FileOffset": 151348, "Value": 0, "Offset": 0}, "Structure": "IMAGE_IMPORT_DESCRIPTOR"}, {"Hint": 0, "Name": "QueryWorkingSet", "DLL": "psapi.dll"}], [{"TimeDateStamp": {"FileOffset": 151372, "Value": "0x0        [Thu Jan  1 00:00:00 1970 UTC]", "Offset": 4}, "Name": {"FileOffset": 151380, "Value": 218052, "Offset": 12}, "ForwarderChain": {"FileOffset": 151376, "Value": 0, "Offset": 8}, "OriginalFirstThunk": {"FileOffset": 151368, "Value": 0, "Offset": 0}, "FirstThunk": {"FileOffset": 151384, "Value": 218012, "Offset": 16}, "Characteristics": {"FileOffset": 151368, "Value": 0, "Offset": 0}, "Structure": "IMAGE_IMPORT_DESCRIPTOR"}, {"Hint": 0, "Name": "IsMenu", "DLL": "user32.dll"}]], "PE Sections": [{"PointerToRawData": {"FileOffset": 460, "Value": 1024, "Offset": 20}, "SHA1": "da39a3ee5e6b4b0d3255bfef95601890afd80709", "SHA256": "e3b0c44298fc1c149afbf4c8996fb92427ae41e4649b934ca495991b7852b855", "Name": {"FileOffset": 440, "Value": "UPX0", "Offset": 0}, "NumberOfRelocations": {"FileOffset": 472, "Value": 0, "Offset": 32}, "Misc_VirtualSize": {"FileOffset": 448, "Value": 61440, "Offset": 8}, "Characteristics": {"FileOffset": 476, "Value": 3758096512, "Offset": 36}, "Misc": {"FileOffset": 448, "Value": 61440, "Offset": 8}, "PointerToLinenumbers": {"FileOffset": 468, "Value": 0, "Offset": 28}, "SizeOfRawData": {"FileOffset": 456, "Value": 0, "Offset": 16}, "Misc_PhysicalAddress": {"FileOffset": 448, "Value": 61440, "Offset": 8}, "PointerToRelocations": {"FileOffset": 464, "Value": 0, "Offset": 24}, "Flags": ["IMAGE_SCN_MEM_EXECUTE", "IMAGE_SCN_MEM_WRITE", "IMAGE_SCN_CNT_UNINITIALIZED_DATA", "IMAGE_SCN_MEM_READ"], "SHA512": "cf83e1357eefb8bdf1542850d66d8007d620e4050b5715dc83f4a921d36ce9ce47d0d13c5d85f2b0ff8318d2877eec2f63b931bd47417a81a538327af927da3e", "MD5": "d41d8cd98f00b204e9800998ecf8427e", "Entropy": 0.0, "VirtualAddress": {"FileOffset": 452, "Value": 4096, "Offset": 12}, "Structure": "IMAGE_SECTION_HEADER", "NumberOfLinenumbers": {"FileOffset": 474, "Value": 0, "Offset": 34}}, {"PointerToRawData": {"FileOffset": 500, "Value": 1024, "Offset": 20}, "SHA1": "80535fb66d573acdc1ec67ad5391a01d13ceace0", "SHA256": "f161eedcb7316e3640304560019c1fc8af5c86964c1a3281488b958765f032f9", "Name": {"FileOffset": 480, "Value": "UPX1", "Offset": 0}, "NumberOfRelocations": {"FileOffset": 512, "Value": 0, "Offset": 32}, "Misc_VirtualSize": {"FileOffset": 488, "Value": 151552, "Offset": 8}, "Characteristics": {"FileOffset": 516, "Value": 3758096448, "Offset": 36}, "Misc": {"FileOffset": 488, "Value": 151552, "Offset": 8}, "PointerToLinenumbers": {"FileOffset": 508, "Value": 0, "Offset": 28}, "SizeOfRawData": {"FileOffset": 496, "Value": 149504, "Offset": 16}, "Misc_PhysicalAddress": {"FileOffset": 488, "Value": 151552, "Offset": 8}, "PointerToRelocations": {"FileOffset": 504, "Value": 0, "Offset": 24}, "Flags": ["IMAGE_SCN_MEM_EXECUTE", "IMAGE_SCN_CNT_INITIALIZED_DATA", "IMAGE_SCN_MEM_WRITE", "IMAGE_SCN_MEM_READ"], "SHA512": "0af461eee25abd1701482dbbea5795f636d98adc2ee78f505db9544ae7b821afc09ebf37c3bdf17a25717545ed779a9203b22ef7db5deac9d2f45289dfde5743", "MD5": "ea0f94cefba357501d97512923af2dc2", "Entropy": 7.8975663468228365, "VirtualAddress": {"FileOffset": 492, "Value": 65536, "Offset": 12}, "Structure": "IMAGE_SECTION_HEADER", "NumberOfLinenumbers": {"FileOffset": 514, "Value": 0, "Offset": 34}}, {"PointerToRawData": {"FileOffset": 540, "Value": 150528, "Offset": 20}, "SHA1": "8321366482cc1edd26381e64d6d22fbc80d2f80c", "SHA256": "56d97377235b00c5051dc1ef8b0153eebdb4dd972d47429d9f001ee3096476a2", "Name": {"FileOffset": 520, "Value": ".rsrc", "Offset": 0}, "NumberOfRelocations": {"FileOffset": 552, "Value": 0, "Offset": 32}, "Misc_VirtualSize": {"FileOffset": 528, "Value": 4096, "Offset": 8}, "Characteristics": {"FileOffset": 556, "Value": 3221225536, "Offset": 36}, "Misc": {"FileOffset": 528, "Value": 4096, "Offset": 8}, "PointerToLinenumbers": {"FileOffset": 548, "Value": 0, "Offset": 28}, "SizeOfRawData": {"FileOffset": 536, "Value": 1536, "Offset": 16}, "Misc_PhysicalAddress": {"FileOffset": 528, "Value": 4096, "Offset": 8}, "PointerToRelocations": {"FileOffset": 544, "Value": 0, "Offset": 24}, "Flags": ["IMAGE_SCN_CNT_INITIALIZED_DATA", "IMAGE_SCN_MEM_WRITE", "IMAGE_SCN_MEM_READ"], "SHA512": "939d58417ab56f194071ca8f85db894d81e9f78eb1ccab6380e5fba9ac57c9d3d5ec2f3232ec6d66f1f778492f101f823bdd79dbdc507000e7d5694b3540705a", "MD5": "6a62ccaabf0276fb2db82cb928fbd1a3", "Entropy": 2.8615198532318913, "VirtualAddress": {"FileOffset": 532, "Value": 217088, "Offset": 12}, "Structure": "IMAGE_SECTION_HEADER", "NumberOfLinenumbers": {"FileOffset": 554, "Value": 0, "Offset": 34}}], "Resource directory": [{"MajorVersion": {"FileOffset": 150536, "Value": 0, "Offset": 8}, "NumberOfIdEntries": {"FileOffset": 150542, "Value": 1, "Offset": 14}, "MinorVersion": {"FileOffset": 150538, "Value": 0, "Offset": 10}, "TimeDateStamp": {"FileOffset": 150532, "Value": "0x0        [Thu Jan  1 00:00:00 1970 UTC]", "Offset": 4}, "Characteristics": {"FileOffset": 150528, "Value": 0, "Offset": 0}, "NumberOfNamedEntries": {"FileOffset": 150540, "Value": 0, "Offset": 12}, "Structure": "IMAGE_RESOURCE_DIRECTORY"}, {"Structure": "IMAGE_RESOURCE_DIRECTORY_ENTRY", "Id": [16, "RT_VERSION"], "OffsetToData": {"FileOffset": 150548, "Value": 2147483672, "Offset": 4}, "Name": {"FileOffset": 150544, "Value": 16, "Offset": 0}}, [{"MajorVersion": {"FileOffset": 150560, "Value": 0, "Offset": 8}, "NumberOfIdEntries": {"FileOffset": 150566, "Value": 1, "Offset": 14}, "MinorVersion": {"FileOffset": 150562, "Value": 0, "Offset": 10}, "TimeDateStamp": {"FileOffset": 150556, "Value": "0x0        [Thu Jan  1 00:00:00 1970 UTC]", "Offset": 4}, "Characteristics": {"FileOffset": 150552, "Value": 0, "Offset": 0}, "NumberOfNamedEntries": {"FileOffset": 150564, "Value": 0, "Offset": 12}, "Structure": "IMAGE_RESOURCE_DIRECTORY"}, {"Structure": "IMAGE_RESOURCE_DIRECTORY_ENTRY", "Id": 1, "OffsetToData": {"FileOffset": 150572, "Value": 2147483696, "Offset": 4}, "Name": {"FileOffset": 150568, "Value": 1, "Offset": 0}}, [{"MajorVersion": {"FileOffset": 150584, "Value": 0, "Offset": 8}, "NumberOfIdEntries": {"FileOffset": 150590, "Value": 1, "Offset": 14}, "MinorVersion": {"FileOffset": 150586, "Value": 0, "Offset": 10}, "TimeDateStamp": {"FileOffset": 150580, "Value": "0x0        [Thu Jan  1 00:00:00 1970 UTC]", "Offset": 4}, "Characteristics": {"FileOffset": 150576, "Value": 0, "Offset": 0}, "NumberOfNamedEntries": {"FileOffset": 150588, "Value": 0, "Offset": 12}, "Structure": "IMAGE_RESOURCE_DIRECTORY"}, {"LANG": 9, "SUBLANG_NAME": "SUBLANG_ENGLISH_US", "Name": {"FileOffset": 150592, "Value": 1033, "Offset": 0}, "CodePage": {"FileOffset": 150608, "Value": 0, "Offset": 8}, "LANG_NAME": "LANG_ENGLISH", "OffsetToData": {"FileOffset": 150600, "Value": 217180, "Offset": 0}, "Reserved": {"FileOffset": 150612, "Value": 0, "Offset": 12}, "SUBLANG": 1, "Structure": "IMAGE_RESOURCE_DATA_ENTRY", "Size": {"FileOffset": 150604, "Value": 688, "Offset": 4}}]]]}
